README.md
setup.py
cleverbot3/__init__.py
cleverbot3/cleverbot.py
cleverbot3.egg-info/PKG-INFO
cleverbot3.egg-info/SOURCES.txt
cleverbot3.egg-info/dependency_links.txt
cleverbot3.egg-info/top_level.txt