Metadata-Version: 1.1
Name: cleverbot3
Version: 0.1.2
Summary: An API for Cleverbot in Python 3
Home-page: https://github.com/Corwind/cleverbot3.py
Author: Guillaume Doré
Author-email: guillaume@dore-net.fr
License: Beer-Ware
Platform: UNKNOWN
Classifier: Programming Language :: Python
Classifier: Programming Language :: Python :: 3
Classifier: Operating System :: OS Independent
